django_serializable_model.py
serializable.py
django_serializable_model-0.0.6.dist-info/LICENSE
django_serializable_model-0.0.6.dist-info/METADATA
django_serializable_model-0.0.6.dist-info/WHEEL
django_serializable_model-0.0.6.dist-info/top_level.txt
django_serializable_model-0.0.6.dist-info/RECORD
