Metadata-Version: 2.1
Name: django-serializable-model
Version: 0.0.6
Summary: Django classes to make your models, managers, and querysets serializable, with built-in support for related objects in ~150 LoC
Home-page: https://github.com/agilgur5/django-serializable-model
Author: Anton Gilgur
License: Apache-2.0
Project-URL: Source, https://github.com/agilgur5/django-serializable-model/
Project-URL: Tracker, https://github.com/agilgur5/django-serializable-model/issues
Keywords: django serializer serializers serializer-django serialize json dict queryset model modelmanager full wadofstuff
Platform: UNKNOWN
Classifier: Natural Language :: English
Classifier: Intended Audience :: Developers
Classifier: Topic :: Software Development :: Libraries
Classifier: License :: OSI Approved :: Apache Software License
Classifier: Development Status :: 3 - Alpha
Classifier: Operating System :: OS Independent
Classifier: Programming Language :: Python :: 2
Classifier: Programming Language :: Python :: 2.7
Classifier: Programming Language :: Python :: 3
Classifier: Framework :: Django
Classifier: Framework :: Django :: 1.4
Classifier: Framework :: Django :: 1.5
Classifier: Framework :: Django :: 1.6
Classifier: Framework :: Django :: 1.7
Classifier: Framework :: Django :: 1.8
Classifier: Framework :: Django :: 1.9
Classifier: Framework :: Django :: 1.10
Classifier: Framework :: Django :: 1.11
Classifier: Framework :: Django :: 2.0
Classifier: Framework :: Django :: 2.1
Classifier: Framework :: Django :: 2.2
Requires-Python: >=2.7, <4
